nicegui_router/__init__.py
nicegui_router/dynamic_router.py
nicegui_router/logging.py
nicegui_router/reactive.py
nicegui_router/route_decorator.py
nicegui_router/theme.py
nicegui_router-0.0.4.dist-info/LICENSE
nicegui_router-0.0.4.dist-info/METADATA
nicegui_router-0.0.4.dist-info/WHEEL
nicegui_router-0.0.4.dist-info/top_level.txt
nicegui_router-0.0.4.dist-info/RECORD
