Metadata-Version: 2.2
Name: nicegui-router
Version: 0.0.4
Summary: File-based routing and theming for NiceGUI, bringing structured navigation and consistent page themes
Home-page: https://github.com/puntorigen/nicegui-router
Author: Pablo Schaffner
Author-email: pablo@puntorigen.com
Classifier: Programming Language :: Python :: 3
Classifier: License :: OSI Approved :: MIT License
Classifier: Operating System :: OS Independent
Requires-Python: >=3.6
License-File: LICENSE
Requires-Dist: nicegui>=2.3.0
Requires-Dist: PyJWT==2.9.0
Requires-Dist: uvicorn==0.34.0
Dynamic: author
Dynamic: author-email
Dynamic: classifier
Dynamic: description
Dynamic: description-content-type
Dynamic: home-page
Dynamic: requires-dist
Dynamic: requires-python
Dynamic: summary
